{"nodes": [{"id": "workflowoptions", "label": "workflowOptions.ts", "file_type": "code", "source_file": "frontend\\src\\ops\\workflowOptions.ts", "source_location": "L1"}, {"id": "workflowoptions_normalizeworkflowkey", "label": "normalizeWorkflowKey()", "file_type": "code", "source_file": "frontend\\src\\ops\\workflowOptions.ts", "source_location": "L55"}, {"id": "workflowoptions_tasktypelabel", "label": "taskTypeLabel()", "file_type": "code", "source_file": "frontend\\src\\ops\\workflowOptions.ts", "source_location": "L63"}, {"id": "workflowoptions_departmentlabel", "label": "departmentLabel()", "file_type": "code", "source_file": "frontend\\src\\ops\\workflowOptions.ts", "source_location": "L70"}, {"id": "workflowoptions_projectstagelabel", "label": "projectStageLabel()", "file_type": "code", "source_file": "frontend\\src\\ops\\workflowOptions.ts", "source_location": "L77"}, {"id": "workflowoptions_tasktypevalueoptions", "label": "taskTypeValueOptions()", "file_type": "code", "source_file": "frontend\\src\\ops\\workflowOptions.ts", "source_location": "L83"}, {"id": "workflowoptions_departmentvalueoptions", "label": "departmentValueOptions()", "file_type": "code", "source_file": "frontend\\src\\ops\\workflowOptions.ts", "source_location": "L87"}, {"id": "workflowoptions_projectstagevalueoptions", "label": "projectStageValueOptions()", "file_type": "code", "source_file": "frontend\\src\\ops\\workflowOptions.ts", "source_location": "L91"}], "edges": [{"source": "workflowoptions", "target": "workflowoptions_normalizeworkflowkey", "relation": "contains", "confidence": "EXTRACTED", "source_file": "frontend\\src\\ops\\workflowOptions.ts", "source_location": "L55", "weight": 1.0}, {"source": "workflowoptions", "target": "workflowoptions_tasktypelabel", "relation": "contains", "confidence": "EXTRACTED", "source_file": "frontend\\src\\ops\\workflowOptions.ts", "source_location": "L63", "weight": 1.0}, {"source": "workflowoptions", "target": "workflowoptions_departmentlabel", "relation": "contains", "confidence": "EXTRACTED", "source_file": "frontend\\src\\ops\\workflowOptions.ts", "source_location": "L70", "weight": 1.0}, {"source": "workflowoptions", "target": "workflowoptions_projectstagelabel", "relation": "contains", "confidence": "EXTRACTED", "source_file": "frontend\\src\\ops\\workflowOptions.ts", "source_location": "L77", "weight": 1.0}, {"source": "workflowoptions", "target": "workflowoptions_tasktypevalueoptions", "relation": "contains", "confidence": "EXTRACTED", "source_file": "frontend\\src\\ops\\workflowOptions.ts", "source_location": "L83", "weight": 1.0}, {"source": "workflowoptions", "target": "workflowoptions_departmentvalueoptions", "relation": "contains", "confidence": "EXTRACTED", "source_file": "frontend\\src\\ops\\workflowOptions.ts", "source_location": "L87", "weight": 1.0}, {"source": "workflowoptions", "target": "workflowoptions_projectstagevalueoptions", "relation": "contains", "confidence": "EXTRACTED", "source_file": "frontend\\src\\ops\\workflowOptions.ts", "source_location": "L91", "weight": 1.0}, {"source": "workflowoptions_tasktypelabel", "target": "workflowoptions_normalizeworkflowkey", "relation": "calls", "confidence": "INFERRED", "source_file": "frontend\\src\\ops\\workflowOptions.ts", "source_location": "L66", "weight": 0.8}]}