{"nodes": [{"id": "rolepreviewchecklist_test", "label": "rolePreviewChecklist.test.ts", "file_type": "code", "source_file": "frontend\\src\\preview\\rolePreviewChecklist.test.ts", "source_location": "L1"}], "edges": [{"source": "rolepreviewchecklist_test", "target": "vitest", "relation": "imports_from", "confidence": "EXTRACTED", "source_file": "frontend\\src\\preview\\rolePreviewChecklist.test.ts", "source_location": "L1", "weight": 1.0}, {"source": "rolepreviewchecklist_test", "target": "rolepreviewchecklist", "relation": "imports_from", "confidence": "EXTRACTED", "source_file": "frontend\\src\\preview\\rolePreviewChecklist.test.ts", "source_location": "L3", "weight": 1.0}]}