{"nodes": [{"id": "taskviewpresets", "label": "taskViewPresets.ts", "file_type": "code", "source_file": "frontend\\src\\features\\tasks\\taskViewPresets.ts", "source_location": "L1"}, {"id": "taskviewpresets_normalizetext", "label": "normalizeText()", "file_type": "code", "source_file": "frontend\\src\\features\\tasks\\taskViewPresets.ts", "source_location": "L28"}, {"id": "taskviewpresets_normalizetaskviewpreset", "label": "normalizeTaskViewPreset()", "file_type": "code", "source_file": "frontend\\src\\features\\tasks\\taskViewPresets.ts", "source_location": "L32"}, {"id": "taskviewpresets_collecttaskviewpresets", "label": "collectTaskViewPresets()", "file_type": "code", "source_file": "frontend\\src\\features\\tasks\\taskViewPresets.ts", "source_location": "L48"}, {"id": "taskviewpresets_snapshotfromtaskviewpreset", "label": "snapshotFromTaskViewPreset()", "file_type": "code", "source_file": "frontend\\src\\features\\tasks\\taskViewPresets.ts", "source_location": "L55"}, {"id": "taskviewpresets_buildtaskviewpresetpayload", "label": "buildTaskViewPresetPayload()", "file_type": "code", "source_file": "frontend\\src\\features\\tasks\\taskViewPresets.ts", "source_location": "L68"}, {"id": "taskviewpresets_getdefaulttaskviewpreset", "label": "getDefaultTaskViewPreset()", "file_type": "code", "source_file": "frontend\\src\\features\\tasks\\taskViewPresets.ts", "source_location": "L83"}, {"id": "taskviewpresets_matchestaskviewpreset", "label": "matchesTaskViewPreset()", "file_type": "code", "source_file": "frontend\\src\\features\\tasks\\taskViewPresets.ts", "source_location": "L87"}], "edges": [{"source": "taskviewpresets", "target": "taskdomain", "relation": "imports_from", "confidence": "EXTRACTED", "source_file": "frontend\\src\\features\\tasks\\taskViewPresets.ts", "source_location": "L1", "weight": 1.0}, {"source": "taskviewpresets", "target": "taskviewpresets_normalizetext", "relation": "contains", "confidence": "EXTRACTED", "source_file": "frontend\\src\\features\\tasks\\taskViewPresets.ts", "source_location": "L28", "weight": 1.0}, {"source": "taskviewpresets", "target": "taskviewpresets_normalizetaskviewpreset", "relation": "contains", "confidence": "EXTRACTED", "source_file": "frontend\\src\\features\\tasks\\taskViewPresets.ts", "source_location": "L32", "weight": 1.0}, {"source": "taskviewpresets", "target": "taskviewpresets_collecttaskviewpresets", "relation": "contains", "confidence": "EXTRACTED", "source_file": "frontend\\src\\features\\tasks\\taskViewPresets.ts", "source_location": "L48", "weight": 1.0}, {"source": "taskviewpresets", "target": "taskviewpresets_snapshotfromtaskviewpreset", "relation": "contains", "confidence": "EXTRACTED", "source_file": "frontend\\src\\features\\tasks\\taskViewPresets.ts", "source_location": "L55", "weight": 1.0}, {"source": "taskviewpresets", "target": "taskviewpresets_buildtaskviewpresetpayload", "relation": "contains", "confidence": "EXTRACTED", "source_file": "frontend\\src\\features\\tasks\\taskViewPresets.ts", "source_location": "L68", "weight": 1.0}, {"source": "taskviewpresets", "target": "taskviewpresets_getdefaulttaskviewpreset", "relation": "contains", "confidence": "EXTRACTED", "source_file": "frontend\\src\\features\\tasks\\taskViewPresets.ts", "source_location": "L83", "weight": 1.0}, {"source": "taskviewpresets", "target": "taskviewpresets_matchestaskviewpreset", "relation": "contains", "confidence": "EXTRACTED", "source_file": "frontend\\src\\features\\tasks\\taskViewPresets.ts", "source_location": "L87", "weight": 1.0}, {"source": "taskviewpresets_normalizetaskviewpreset", "target": "taskviewpresets_normalizetext", "relation": "calls", "confidence": "INFERRED", "source_file": "frontend\\src\\features\\tasks\\taskViewPresets.ts", "source_location": "L35", "weight": 0.8}, {"source": "taskviewpresets_buildtaskviewpresetpayload", "target": "taskviewpresets_normalizetext", "relation": "calls", "confidence": "INFERRED", "source_file": "frontend\\src\\features\\tasks\\taskViewPresets.ts", "source_location": "L70", "weight": 0.8}, {"source": "taskviewpresets_matchestaskviewpreset", "target": "taskviewpresets_snapshotfromtaskviewpreset", "relation": "calls", "confidence": "INFERRED", "source_file": "frontend\\src\\features\\tasks\\taskViewPresets.ts", "source_location": "L88", "weight": 0.8}]}