{"nodes": [{"id": "revisequotationmapper", "label": "reviseQuotationMapper.ts", "file_type": "code", "source_file": "backend\\src\\modules\\quotations\\mappers\\reviseQuotationMapper.ts", "source_location": "L1"}, {"id": "revisequotationmapper_maprevisequotationinput", "label": "mapReviseQuotationInput()", "file_type": "code", "source_file": "backend\\src\\modules\\quotations\\mappers\\reviseQuotationMapper.ts", "source_location": "L12"}], "edges": [{"source": "revisequotationmapper", "target": "common", "relation": "imports_from", "confidence": "EXTRACTED", "source_file": "backend\\src\\modules\\quotations\\mappers\\reviseQuotationMapper.ts", "source_location": "L1", "weight": 1.0}, {"source": "revisequotationmapper", "target": "typedstate", "relation": "imports_from", "confidence": "EXTRACTED", "source_file": "backend\\src\\modules\\quotations\\mappers\\reviseQuotationMapper.ts", "source_location": "L2", "weight": 1.0}, {"source": "revisequotationmapper", "target": "revisequotationmapper_maprevisequotationinput", "relation": "contains", "confidence": "EXTRACTED", "source_file": "backend\\src\\modules\\quotations\\mappers\\reviseQuotationMapper.ts", "source_location": "L12", "weight": 1.0}]}